{
  "birthday": "1995-02-12",
  "age": 30,
  "height": "158",
  "bust": "83",
  "waistline": "59",
  "hipline": "86",
  "birthplace": "不明",
  "cup": "D",
  "twitter": "https://twitter.com/yukitake_life",
  "av_league_comments": [
    {
      "comment": "欲しい欲しい欲しい。",
      "commenter": "名無し",
      "date": "2025-11-22",
      "time": "17:16",
      "user_id": "12485"
    },
    {
      "comment": "可愛い欲しいしたい。綺麗美人。これからも大好きなエッチをしてみなを幸せにして自分も最高に気持ちいいセックスをして幸せに。",
      "commenter": "名無し",
      "date": "2025-11-22",
      "time": "17:14",
      "user_id": "12484"
    },
    {
      "comment": "有紀さんの絡みは最高です。感じているのがモロに伝わってくるからです。ファンになりました、引退しないでください。まだまだ有紀さんのパーフェクトボデイを堪能したいです。",
      "commenter": "名無し",
      "date": null,
      "time": null,
      "user_id": null
    },
    {
      "comment": "可愛いキレイエロい毎日会いたい見たいコスらずにはいられない。",
      "commenter": "名無し",
      "date": "2025-07-05",
      "time": "17:58",
      "user_id": "10428"
    },
    {
      "comment": "もっともっと激しい作品を期待しています。アンアン喘ぎが好きなのでアンアン連発喘ぎお願いします。引退作品はアンアン喘ぎまくり期待しています。",
      "commenter": "名無し",
      "date": "2025-07-05",
      "time": "17:11",
      "user_id": "10427"
    },
    {
      "comment": "竹内有紀さんの、顔写真あまり良くないと思ってた、所が動画作品、(町内キャンプ)見て綺麗で美人顔に、ビックリ応援したいと思いますので、頑張って下さい、",
      "commenter": "名無し",
      "date": "2025-06-06",
      "time": "21:55",
      "user_id": "10091"
    },
    {
      "comment": "函館市深堀町に住んでいます。竹内有紀さんと、おつきあいしたいです。結婚したいです。よろしくお願いいたします。",
      "commenter": "名無し",
      "date": null,
      "time": null,
      "user_id": null
    },
    {
      "comment": "竹内さん色気ありすぎ",
      "commenter": "名無し",
      "date": "2024-09-16",
      "time": "17:19",
      "user_id": "5419"
    },
    {
      "comment": "竹内有紀初めましてオナニ姿見せて下さい宜しくお願いは",
      "commenter": "名無し",
      "date": null,
      "time": null,
      "user_id": null
    }
  ],
  "data_source": "av-league",
  "data_source_url": "https://www.av-league.com/actress/5473.html"
}